unionllm/__init__.py
unionllm/exceptions.py
unionllm/main.py
unionllm/models.py
unionllm/providers/__init__.py
unionllm/providers/azure.py
unionllm/providers/baichuan.py
unionllm/providers/base_provider.py
unionllm/providers/coze.py
unionllm/providers/coze_back.py
unionllm/providers/deepseek.py
unionllm/providers/dify.py
unionllm/providers/doubao.py
unionllm/providers/fastgpt.py
unionllm/providers/gemini.py
unionllm/providers/lingyi.py
unionllm/providers/litellm.py
unionllm/providers/minimax.py
unionllm/providers/moonshot.py
unionllm/providers/qwen.py
unionllm/providers/stepfun.py
unionllm/providers/tiangong.py
unionllm/providers/wenxin.py
unionllm/providers/xai.py
unionllm/providers/xunfei.py
unionllm/providers/xunfei_http.py
unionllm/providers/zhipu.py
unionllm/utils.py
unionllm-0.2.9.dist-info/LICENSE
unionllm-0.2.9.dist-info/METADATA
unionllm-0.2.9.dist-info/WHEEL
unionllm-0.2.9.dist-info/RECORD
