Metadata-Version: 2.1
Name: unionllm
Version: 0.2.9
Summary: A Python library for unified access to all kinds of large language models.
Home-page: https://github.com/EvalsOne/UnionLLM
License: MIT
Author: evalsone
Author-email: contact@evalsone.com
Classifier: License :: OSI Approved :: MIT License
Classifier: Programming Language :: Python :: 2
Classifier: Programming Language :: Python :: 2.7
Classifier: Programming Language :: Python :: 3
Classifier: Programming Language :: Python :: 3.4
Classifier: Programming Language :: Python :: 3.5
Classifier: Programming Language :: Python :: 3.6
Classifier: Programming Language :: Python :: 3.7
Classifier: Programming Language :: Python :: 3.8
Classifier: Programming Language :: Python :: 3.9
Classifier: Programming Language :: Python :: 3.10
Classifier: Programming Language :: Python :: 3.11
Classifier: Programming Language :: Python :: 3.12
Requires-Dist: dashscope
Requires-Dist: litellm
Requires-Dist: openai
Requires-Dist: pydantic
Requires-Dist: requests
Requires-Dist: tenacity
Requires-Dist: websocket-client
Requires-Dist: zhipuai
